lbinstall/DependencyManager.py
lbinstall/Graph.py
lbinstall/InstallAreaManager.py
lbinstall/Installer.py
lbinstall/LCGYumConsistency.py
lbinstall/LHCbConfig.py
lbinstall/LbInstall.py
lbinstall/LbRpmTarCompare.py
lbinstall/LbYumConsistency.py
lbinstall/Model.py
lbinstall/PackageManager.py
lbinstall/RpmTarTool.py
lbinstall/YumChecker.py
lbinstall/__init__.py
lbinstall/db/ChainedDBManager.py
lbinstall/db/DBManager.py
lbinstall/db/__init__.py
lbinstall/db/model.py
lbinstall/db/test/TestChainedDB.py
lbinstall/db/test/TestChainedDBManager.py
lbinstall/db/test/TestChainedDBOps.py
lbinstall/db/test/TestDB.py
lbinstall/db/test/TestDBManager.py
lbinstall/db/test/TestDBManagerDep.py
lbinstall/db/test/TestDBManagerRemove.py
lbinstall/db/test/__init__.py
lbinstall/extra/ExtractionChecker.py
lbinstall/extra/RPMExtractor.py
lbinstall/extra/ThreadPoolManager.py
lbinstall/extra/Utils.py
lbinstall/extra/__init__.py
lbinstall/extra/test/TestInstallAreaImporter.py
lbinstall/extra/test/TestRPMExtractor.py
lbinstall/extra/test/TestThreadPoolManager.py
lbinstall/extra/test/__init__.py
lbinstall/rpmfile/__init__.py
lbinstall/rpmfile/cpiofile.py
lbinstall/rpmfile/errors.py
lbinstall/rpmfile/headers.py
lbinstall/rpmfile/io_extra.py
lbinstall/rpmfile/rpmdefs.py
lbinstall/rpmfile/tests/__init__.py
lbinstall/rpmfile/tests/test_subfile.py
lbinstall/test/TestComparison.py
lbinstall/test/TestDependencyManager.py
lbinstall/test/TestFullLbInstall.py
lbinstall/test/TestInstaller.py
lbinstall/test/TestInstallerRemove.py
lbinstall/test/TestInstallerUpdate.py
lbinstall/test/TestLbInstall.py
lbinstall/test/TestPackageManager.py
lbinstall/test/__init__.py
lbinstall-2.0.16.dist-info/LICENSE
lbinstall-2.0.16.dist-info/METADATA
lbinstall-2.0.16.dist-info/WHEEL
lbinstall-2.0.16.dist-info/entry_points.txt
lbinstall-2.0.16.dist-info/top_level.txt
lbinstall-2.0.16.dist-info/RECORD
