Metadata-Version: 2.1
Name: lbinstall
Version: 2.0.16
Summary: LHCb package installation tool
Home-page: https://gitlab.cern.ch/lhcb-core/lbinstall
Author: CERN - LHCb Core Software
Author-email: lhcb-core-soft@cern.ch
License: GPL
Keywords: LHCb
Platform: UNKNOWN
Classifier: Development Status :: 3 - Alpha
Classifier: License :: OSI Approved :: GNU General Public License v3 (GPLv3)
Classifier: Programming Language :: Python :: 2.6
Classifier: Programming Language :: Python :: 2.7
Classifier: Programming Language :: Python :: 3.5
License-File: LICENSE
Requires-Dist: SQLAlchemy
Requires-Dist: six
Requires-Dist: zstandard
